webrtc_apm/__init__.py
webrtc_apm/webrtc-audio-processing-2-1.dll
webrtc_apm/webrtc_apm.cp311-win_amd64.pyd
webrtc_apm-0.1.6.dist-info/METADATA
webrtc_apm-0.1.6.dist-info/WHEEL
webrtc_apm-0.1.6.dist-info/top_level.txt
webrtc_apm-0.1.6.dist-info/RECORD
