Metadata-Version: 2.4
Name: webrtc-apm
Version: 0.1.6
Summary: Python bindings for WebRTC Audio Processing (APM)
Author: JUNAID
License: MIT
Project-URL: Homepage, https://github.com/youruser/webrtc-apm
Classifier: Programming Language :: Python :: 3
Classifier: License :: OSI Approved :: MIT License
Classifier: Operating System :: Microsoft :: Windows
Requires-Python: >=3.11
